{
  "event_id": "401815765",
  "sport": "mlb",
  "date": "20260615",
  "scraped_at": "2026-06-18T04:33:05.003044+00:00",
  "type": "final",
  "batting": {
    "Liam Hicks": {
      "name": "Liam Hicks",
      "team": "Miami Marlins",
      "ab": "4",
      "r": "0",
      "h": "2",
      "rbi": "0",
      "hr": "0",
      "bb": "0",
      "so": "0",
      "avg": ".281"
    },
    "Otto Lopez": {
      "name": "Otto Lopez",
      "team": "Miami Marlins",
      "ab": "3",
      "r": "0",
      "h": "0",
      "rbi": "0",
      "hr": "0",
      "bb": "1",
      "so": "0",
      "avg": ".339"
    },
    "Kyle Stowers": {
      "name": "Kyle Stowers",
      "team": "Miami Marlins",
      "ab": "4",
      "r": "0",
      "h": "0",
      "rbi": "0",
      "hr": "0",
      "bb": "0",
      "so": "3",
      "avg": ".211"
    },
    "Xavier Edwards": {
      "name": "Xavier Edwards",
      "team": "Miami Marlins",
      "ab": "3",
      "r": "0",
      "h": "0",
      "rbi": "0",
      "hr": "0",
      "bb": "1",
      "so": "2",
      "avg": ".296"
    },
    "Cade Gibson": {
      "name": "Cade Gibson",
      "team": "Miami Marlins",
      "ab": "0",
      "r": "0",
      "h": "0",
      "rbi": "0",
      "hr": "0",
      "bb": "0",
      "so": "0",
      "avg": ".000"
    },
    "Heriberto Hernandez": {
      "name": "Heriberto Hernandez",
      "team": "Miami Marlins",
      "ab": "4",
      "r": "0",
      "h": "1",
      "rbi": "0",
      "hr": "0",
      "bb": "0",
      "so": "2",
      "avg": ".237"
    },
    "Owen Caissie": {
      "name": "Owen Caissie",
      "team": "Miami Marlins",
      "ab": "2",
      "r": "0",
      "h": "0",
      "rbi": "0",
      "hr": "0",
      "bb": "0",
      "so": "2",
      "avg": ".209"
    },
    "Esteury Ruiz": {
      "name": "Esteury Ruiz",
      "team": "Miami Marlins",
      "ab": "2",
      "r": "0",
      "h": "0",
      "rbi": "0",
      "hr": "0",
      "bb": "0",
      "so": "1",
      "avg": ".220"
    },
    "Jakob Marsee": {
      "name": "Jakob Marsee",
      "team": "Miami Marlins",
      "ab": "4",
      "r": "0",
      "h": "1",
      "rbi": "0",
      "hr": "0",
      "bb": "0",
      "so": "2",
      "avg": ".201"
    },
    "Joe Mack": {
      "name": "Joe Mack",
      "team": "Miami Marlins",
      "ab": "1",
      "r": "0",
      "h": "1",
      "rbi": "0",
      "hr": "0",
      "bb": "1",
      "so": "0",
      "avg": ".247"
    },
    "William Kempner": {
      "name": "William Kempner",
      "team": "Miami Marlins",
      "ab": "0",
      "r": "0",
      "h": "0",
      "rbi": "0",
      "hr": "0",
      "bb": "0",
      "so": "0",
      "avg": ".000"
    },
    "Leo Jimenez": {
      "name": "Leo Jimenez",
      "team": "Miami Marlins",
      "ab": "1",
      "r": "0",
      "h": "0",
      "rbi": "0",
      "hr": "0",
      "bb": "0",
      "so": "0",
      "avg": ".188"
    },
    "Connor Norby": {
      "name": "Connor Norby",
      "team": "Miami Marlins",
      "ab": "1",
      "r": "0",
      "h": "0",
      "rbi": "0",
      "hr": "0",
      "bb": "0",
      "so": "1",
      "avg": ".211"
    },
    "Javier Sanoja": {
      "name": "Javier Sanoja",
      "team": "Miami Marlins",
      "ab": "3",
      "r": "0",
      "h": "0",
      "rbi": "0",
      "hr": "0",
      "bb": "0",
      "so": "0",
      "avg": ".248"
    },
    "Kyle Schwarber": {
      "name": "Kyle Schwarber",
      "team": "Philadelphia Phillies",
      "ab": "4",
      "r": "0",
      "h": "1",
      "rbi": "0",
      "hr": "0",
      "bb": "1",
      "so": "2",
      "avg": ".247"
    },
    "Trea Turner": {
      "name": "Trea Turner",
      "team": "Philadelphia Phillies",
      "ab": "3",
      "r": "0",
      "h": "0",
      "rbi": "0",
      "hr": "0",
      "bb": "0",
      "so": "0",
      "avg": ".216"
    },
    "Alec Bohm": {
      "name": "Alec Bohm",
      "team": "Philadelphia Phillies",
      "ab": "0",
      "r": "0",
      "h": "0",
      "rbi": "1",
      "hr": "0",
      "bb": "0",
      "so": "0",
      "avg": ".219"
    },
    "Bryce Harper": {
      "name": "Bryce Harper",
      "team": "Philadelphia Phillies",
      "ab": "3",
      "r": "0",
      "h": "0",
      "rbi": "1",
      "hr": "0",
      "bb": "1",
      "so": "0",
      "avg": ".253"
    },
    "Brandon Marsh": {
      "name": "Brandon Marsh",
      "team": "Philadelphia Phillies",
      "ab": "5",
      "r": "1",
      "h": "2",
      "rbi": "0",
      "hr": "0",
      "bb": "0",
      "so": "2",
      "avg": ".324"
    },
    "Bryson Stott": {
      "name": "Bryson Stott",
      "team": "Philadelphia Phillies",
      "ab": "2",
      "r": "2",
      "h": "0",
      "rbi": "0",
      "hr": "0",
      "bb": "2",
      "so": "0",
      "avg": ".230"
    },
    "J.T. Realmuto": {
      "name": "J.T. Realmuto",
      "team": "Philadelphia Phillies",
      "ab": "4",
      "r": "1",
      "h": "1",
      "rbi": "2",
      "hr": "1",
      "bb": "0",
      "so": "0",
      "avg": ".211"
    },
    "Gabriel Rincones Jr.": {
      "name": "Gabriel Rincones Jr.",
      "team": "Philadelphia Phillies",
      "ab": "4",
      "r": "1",
      "h": "1",
      "rbi": "2",
      "hr": "1",
      "bb": "0",
      "so": "0",
      "avg": ".143"
    },
    "Derek Hill": {
      "name": "Derek Hill",
      "team": "Philadelphia Phillies",
      "ab": "0",
      "r": "0",
      "h": "0",
      "rbi": "0",
      "hr": "0",
      "bb": "0",
      "so": "0",
      "avg": ".250"
    },
    "Justin Crawford": {
      "name": "Justin Crawford",
      "team": "Philadelphia Phillies",
      "ab": "4",
      "r": "1",
      "h": "3",
      "rbi": "1",
      "hr": "0",
      "bb": "0",
      "so": "0",
      "avg": ".241"
    },
    "Edmundo Sosa": {
      "name": "Edmundo Sosa",
      "team": "Philadelphia Phillies",
      "ab": "4",
      "r": "1",
      "h": "2",
      "rbi": "0",
      "hr": "0",
      "bb": "0",
      "so": "0",
      "avg": ".231"
    }
  },
  "pitching": {
    "Ryan Gusto": {
      "name": "Ryan Gusto",
      "team": "Miami Marlins",
      "ip": "4.2",
      "h": "8",
      "r": "5",
      "er": "5",
      "bb": "3",
      "so": "1",
      "hr": "2",
      "era": "7.24",
      "pitches": "91"
    },
    "William Kempner": {
      "name": "William Kempner",
      "team": "Miami Marlins",
      "ip": "2.1",
      "h": "0",
      "r": "0",
      "er": "0",
      "bb": "0",
      "so": "2",
      "hr": "0",
      "era": "0.00",
      "pitches": "33"
    },
    "Cade Gibson": {
      "name": "Cade Gibson",
      "team": "Miami Marlins",
      "ip": "1.0",
      "h": "2",
      "r": "2",
      "er": "2",
      "bb": "1",
      "so": "1",
      "hr": "0",
      "era": "6.75",
      "pitches": "29"
    },
    "Zack Wheeler": {
      "name": "Zack Wheeler",
      "team": "Philadelphia Phillies",
      "ip": "6.0",
      "h": "2",
      "r": "0",
      "er": "0",
      "bb": "3",
      "so": "9",
      "hr": "0",
      "era": "2.01",
      "pitches": "97"
    },
    "Tim Mayza": {
      "name": "Tim Mayza",
      "team": "Philadelphia Phillies",
      "ip": "1.0",
      "h": "1",
      "r": "0",
      "er": "0",
      "bb": "0",
      "so": "1",
      "hr": "0",
      "era": "3.16",
      "pitches": "17"
    },
    "Jonathan Bowlan": {
      "name": "Jonathan Bowlan",
      "team": "Philadelphia Phillies",
      "ip": "1.0",
      "h": "1",
      "r": "0",
      "er": "0",
      "bb": "0",
      "so": "2",
      "hr": "0",
      "era": "3.74",
      "pitches": "20"
    },
    "Chase Shugart": {
      "name": "Chase Shugart",
      "team": "Philadelphia Phillies",
      "ip": "1.0",
      "h": "1",
      "r": "0",
      "er": "0",
      "bb": "0",
      "so": "1",
      "hr": "0",
      "era": "3.00",
      "pitches": "12"
    }
  },
  "score": {
    "away": 0,
    "home": 7
  },
  "away_team": "Miami Marlins",
  "home_team": "Philadelphia Phillies"
}