{
  "team": "GSV",
  "team_id": "129689",
  "sport": "WNBA",
  "games_used": 5,
  "fetched_at": "2026-06-10T04:07:36.541850+00:00",
  "players": {
    "alyssa thomas": {
      "minutes": 32.0,
      "points": 22.0,
      "rebounds": 8.0,
      "assists": 9.0,
      "turnovers": 4.0,
      "steals": 2.0,
      "blocks": 0.0,
      "offensiverebounds": 4.0,
      "defensiverebounds": 4.0,
      "fouls": 1.0,
      "plusminus": 5.0
    },
    "natasha mack": {
      "minutes": 25.0,
      "points": 9.0,
      "rebounds": 10.0,
      "assists": 1.0,
      "turnovers": 2.0,
      "steals": 0.0,
      "blocks": 1.0,
      "offensiverebounds": 2.0,
      "defensiverebounds": 8.0,
      "fouls": 2.0,
      "plusminus": -14.0
    },
    "noemie brochant": {
      "minutes": 29.0,
      "points": 10.0,
      "rebounds": 2.0,
      "assists": 6.0,
      "turnovers": 2.0,
      "steals": 2.0,
      "blocks": 0.0,
      "offensiverebounds": 1.0,
      "defensiverebounds": 1.0,
      "fouls": 2.0,
      "plusminus": -2.0
    },
    "kahleah copper": {
      "minutes": 26.0,
      "points": 9.0,
      "rebounds": 4.0,
      "assists": 1.0,
      "turnovers": 1.0,
      "steals": 0.0,
      "blocks": 0.0,
      "offensiverebounds": 1.0,
      "defensiverebounds": 3.0,
      "fouls": 1.0,
      "plusminus": 6.0
    },
    "monique akoa makani": {
      "minutes": 32.0,
      "points": 19.0,
      "rebounds": 3.0,
      "assists": 3.0,
      "turnovers": 0.0,
      "steals": 1.0,
      "blocks": 0.0,
      "offensiverebounds": 0.0,
      "defensiverebounds": 3.0,
      "fouls": 3.0,
      "plusminus": -4.0
    },
    "dewanna bonner": {
      "minutes": 27.0,
      "points": 3.0,
      "rebounds": 5.0,
      "assists": 0.0,
      "turnovers": 0.0,
      "steals": 0.0,
      "blocks": 1.0,
      "offensiverebounds": 0.0,
      "defensiverebounds": 5.0,
      "fouls": 1.0,
      "plusminus": 1.0
    },
    "jovana nogic": {
      "minutes": 9.0,
      "points": 2.0,
      "rebounds": 0.0,
      "assists": 1.0,
      "turnovers": 1.0,
      "steals": 0.0,
      "blocks": 0.0,
      "offensiverebounds": 0.0,
      "defensiverebounds": 0.0,
      "fouls": 4.0,
      "plusminus": -4.0
    },
    "lexi held": {
      "minutes": 15.0,
      "points": 5.0,
      "rebounds": 2.0,
      "assists": 2.0,
      "turnovers": 2.0,
      "steals": 1.0,
      "blocks": 0.0,
      "offensiverebounds": 1.0,
      "defensiverebounds": 1.0,
      "fouls": 4.0,
      "plusminus": 0.0
    },
    "quionche carter": {
      "minutes": 3.0,
      "points": 2.0,
      "rebounds": 0.0,
      "assists": 0.0,
      "turnovers": 0.0,
      "steals": 1.0,
      "blocks": 0.0,
      "offensiverebounds": 0.0,
      "defensiverebounds": 0.0,
      "fouls": 1.0,
      "plusminus": -3.0
    },
    "valeriane ayayi": {},
    "kyara linskens": {},
    "kayla thornton": {
      "minutes": 28.6,
      "points": 12.0,
      "rebounds": 6.0,
      "assists": 0.6,
      "turnovers": 0.4,
      "steals": 0.8,
      "blocks": 0.2,
      "offensiverebounds": 2.2,
      "defensiverebounds": 3.8,
      "fouls": 2.4,
      "plusminus": 3.6
    },
    "gabby williams": {
      "minutes": 27.2,
      "points": 17.0,
      "rebounds": 4.2,
      "assists": 1.6,
      "turnovers": 1.0,
      "steals": 1.6,
      "blocks": 0.2,
      "offensiverebounds": 0.8,
      "defensiverebounds": 3.4,
      "fouls": 2.2,
      "plusminus": 0.0
    },
    "cecilia zandalasini": {
      "minutes": 20.8,
      "points": 8.0,
      "rebounds": 1.8,
      "assists": 1.6,
      "turnovers": 2.2,
      "steals": 1.8,
      "blocks": 0.0,
      "offensiverebounds": 0.6,
      "defensiverebounds": 1.2,
      "fouls": 1.4,
      "plusminus": 0.6
    },
    "kiah stokes": {
      "minutes": 20.4,
      "points": 3.6,
      "rebounds": 4.6,
      "assists": 1.2,
      "turnovers": 0.4,
      "steals": 0.6,
      "blocks": 1.6,
      "offensiverebounds": 0.8,
      "defensiverebounds": 3.8,
      "fouls": 1.6,
      "plusminus": -5.6
    },
    "veronica burton": {
      "minutes": 29.6,
      "points": 13.0,
      "rebounds": 3.2,
      "assists": 5.6,
      "turnovers": 1.4,
      "steals": 0.2,
      "blocks": 0.2,
      "offensiverebounds": 1.2,
      "defensiverebounds": 2.0,
      "fouls": 3.6,
      "plusminus": 1.0
    },
    "janelle salaun": {
      "minutes": 23.2,
      "points": 14.6,
      "rebounds": 4.2,
      "assists": 1.4,
      "turnovers": 0.6,
      "steals": 0.6,
      "blocks": 0.2,
      "offensiverebounds": 0.8,
      "defensiverebounds": 3.4,
      "fouls": 2.4,
      "plusminus": 0.0
    },
    "tiffany hayes": {
      "minutes": 16.2,
      "points": 6.6,
      "rebounds": 1.8,
      "assists": 2.8,
      "turnovers": 1.0,
      "steals": 0.8,
      "blocks": 0.0,
      "offensiverebounds": 0.2,
      "defensiverebounds": 1.6,
      "fouls": 2.0,
      "plusminus": -1.4
    },
    "kaila charles": {
      "minutes": 15.8,
      "points": 3.2,
      "rebounds": 3.2,
      "assists": 1.0,
      "turnovers": 0.8,
      "steals": 0.8,
      "blocks": 0.4,
      "offensiverebounds": 1.2,
      "defensiverebounds": 2.0,
      "fouls": 2.4,
      "plusminus": 0.2
    },
    "kaitlyn chen": {
      "minutes": 10.4,
      "points": 3.8,
      "rebounds": 0.6,
      "assists": 2.0,
      "turnovers": 0.4,
      "steals": 0.0,
      "blocks": 0.0,
      "offensiverebounds": 0.0,
      "defensiverebounds": 0.6,
      "fouls": 0.6,
      "plusminus": -0.4
    },
    "laeticia amihere": {
      "minutes": 4.0,
      "points": 1.0,
      "rebounds": 2.0,
      "assists": 1.0,
      "turnovers": 0.0,
      "steals": 0.0,
      "blocks": 0.0,
      "offensiverebounds": 2.0,
      "defensiverebounds": 0.0,
      "fouls": 0.5,
      "plusminus": 2.0
    },
    "nadia fingall": {},
    "juste jocyte": {
      "minutes": 8.33,
      "points": 4.33,
      "rebounds": 1.0,
      "assists": 0.67,
      "turnovers": 0.67,
      "steals": 0.0,
      "blocks": 0.0,
      "offensiverebounds": 0.0,
      "defensiverebounds": 1.0,
      "fouls": 0.33,
      "plusminus": 4.33
    },
    "iliana rupert": {
      "points": 0.0,
      "rebounds": 0.0,
      "assists": 0.0,
      "turnovers": 0.0,
      "steals": 0.0,
      "blocks": 0.0,
      "offensiverebounds": 0.0,
      "defensiverebounds": 0.0,
      "fouls": 0.0,
      "plusminus": 0.0
    },
    "ndjakalenga mwenentanda": {
      "minutes": 2.5,
      "points": 0.0,
      "rebounds": 0.5,
      "assists": 0.5,
      "turnovers": 0.5,
      "steals": 0.0,
      "blocks": 0.0,
      "offensiverebounds": 0.0,
      "defensiverebounds": 0.5,
      "fouls": 0.0,
      "plusminus": 4.0
    },
    "stephanie talbot": {
      "minutes": 25.5,
      "points": 8.0,
      "rebounds": 3.5,
      "assists": 4.0,
      "turnovers": 1.0,
      "steals": 0.5,
      "blocks": 1.0,
      "offensiverebounds": 1.0,
      "defensiverebounds": 2.5,
      "fouls": 3.5,
      "plusminus": -1.5
    },
    "nalyssa smith": {
      "minutes": 27.0,
      "points": 10.5,
      "rebounds": 7.5,
      "assists": 1.0,
      "turnovers": 1.5,
      "steals": 0.0,
      "blocks": 0.0,
      "offensiverebounds": 2.0,
      "defensiverebounds": 5.5,
      "fouls": 3.0,
      "plusminus": 7.5
    },
    "a'ja wilson": {
      "minutes": 35.5,
      "points": 28.0,
      "rebounds": 14.5,
      "assists": 3.5,
      "turnovers": 3.0,
      "steals": 0.5,
      "blocks": 2.0,
      "offensiverebounds": 3.5,
      "defensiverebounds": 11.0,
      "fouls": 2.5,
      "plusminus": 11.5
    },
    "chelsea gray": {
      "minutes": 36.0,
      "points": 8.5,
      "rebounds": 4.0,
      "assists": 6.0,
      "turnovers": 4.5,
      "steals": 2.0,
      "blocks": 0.0,
      "offensiverebounds": 0.5,
      "defensiverebounds": 3.5,
      "fouls": 3.5,
      "plusminus": 5.0
    },
    "jackie young": {
      "minutes": 36.5,
      "points": 25.0,
      "rebounds": 6.0,
      "assists": 7.0,
      "turnovers": 1.5,
      "steals": 0.5,
      "blocks": 0.0,
      "offensiverebounds": 0.5,
      "defensiverebounds": 5.5,
      "fouls": 2.0,
      "plusminus": 12.5
    },
    "brianna turner": {
      "minutes": 9.5,
      "points": 2.0,
      "rebounds": 1.5,
      "assists": 0.0,
      "turnovers": 1.0,
      "steals": 0.0,
      "blocks": 0.5,
      "offensiverebounds": 1.0,
      "defensiverebounds": 0.5,
      "fouls": 1.5,
      "plusminus": -0.5
    },
    "kierstan bell": {
      "minutes": 10.5,
      "points": 0.0,
      "rebounds": 0.5,
      "assists": 1.0,
      "turnovers": 0.0,
      "steals": 0.0,
      "blocks": 1.0,
      "offensiverebounds": 0.5,
      "defensiverebounds": 0.0,
      "fouls": 0.5,
      "plusminus": 1.0
    },
    "jewell loyd": {
      "minutes": 28.0,
      "points": 5.0,
      "rebounds": 5.0,
      "assists": 3.0,
      "turnovers": 1.0,
      "steals": 1.0,
      "blocks": 0.0,
      "offensiverebounds": 0.0,
      "defensiverebounds": 5.0,
      "fouls": 4.0,
      "plusminus": 2.0
    },
    "cheyenne parker-tyus": {},
    "janiah barker": {},
    "natasha howard": {
      "minutes": 30.0,
      "points": 12.0,
      "rebounds": 10.0,
      "assists": 0.0,
      "turnovers": 2.0,
      "steals": 0.0,
      "blocks": 0.0,
      "offensiverebounds": 5.0,
      "defensiverebounds": 5.0,
      "fouls": 3.0,
      "plusminus": 8.0
    },
    "nia coffey": {
      "minutes": 35.0,
      "points": 3.0,
      "rebounds": 6.0,
      "assists": 5.0,
      "turnovers": 2.0,
      "steals": 0.0,
      "blocks": 3.0,
      "offensiverebounds": 2.0,
      "defensiverebounds": 4.0,
      "fouls": 3.0,
      "plusminus": 3.0
    },
    "kayla mcbride": {
      "minutes": 32.0,
      "points": 14.0,
      "rebounds": 8.0,
      "assists": 2.0,
      "turnovers": 2.0,
      "steals": 2.0,
      "blocks": 0.0,
      "offensiverebounds": 2.0,
      "defensiverebounds": 6.0,
      "fouls": 0.0,
      "plusminus": -1.0
    },
    "courtney williams": {
      "minutes": 34.0,
      "points": 17.0,
      "rebounds": 7.0,
      "assists": 3.0,
      "turnovers": 3.0,
      "steals": 1.0,
      "blocks": 0.0,
      "offensiverebounds": 1.0,
      "defensiverebounds": 6.0,
      "fouls": 2.0,
      "plusminus": 0.0
    },
    "olivia miles": {
      "minutes": 28.0,
      "points": 28.0,
      "rebounds": 4.0,
      "assists": 7.0,
      "turnovers": 1.0,
      "steals": 0.0,
      "blocks": 3.0,
      "offensiverebounds": 0.0,
      "defensiverebounds": 4.0,
      "fouls": 5.0,
      "plusminus": 14.0
    },
    "antonia delaere": {
      "minutes": 13.0,
      "points": 0.0,
      "rebounds": 0.0,
      "assists": 0.0,
      "turnovers": 1.0,
      "steals": 0.0,
      "blocks": 0.0,
      "offensiverebounds": 0.0,
      "defensiverebounds": 0.0,
      "fouls": 0.0,
      "plusminus": -7.0
    },
    "anastasiia olairi kosu": {
      "minutes": 13.0,
      "points": 8.0,
      "rebounds": 4.0,
      "assists": 0.0,
      "turnovers": 0.0,
      "steals": 0.0,
      "blocks": 0.0,
      "offensiverebounds": 1.0,
      "defensiverebounds": 3.0,
      "fouls": 0.0,
      "plusminus": -4.0
    },
    "teaira mccowan": {
      "minutes": 2.0,
      "points": 0.0,
      "rebounds": 2.0,
      "assists": 0.0,
      "turnovers": 0.0,
      "steals": 0.0,
      "blocks": 0.0,
      "offensiverebounds": 2.0,
      "defensiverebounds": 0.0,
      "fouls": 1.0,
      "plusminus": -1.0
    },
    "maya caldwell": {
      "minutes": 12.0,
      "points": 5.0,
      "rebounds": 2.0,
      "assists": 1.0,
      "turnovers": 1.0,
      "steals": 1.0,
      "blocks": 1.0,
      "offensiverebounds": 1.0,
      "defensiverebounds": 1.0,
      "fouls": 1.0,
      "plusminus": 3.0
    },
    "napheesa collier": {},
    "dorka juhasz": {},
    "emma cechova": {},
    "bridget carleton": {
      "minutes": 30.0,
      "points": 11.0,
      "rebounds": 3.0,
      "assists": 1.0,
      "turnovers": 0.0,
      "steals": 1.0,
      "blocks": 0.0,
      "offensiverebounds": 1.0,
      "defensiverebounds": 2.0,
      "fouls": 4.0,
      "plusminus": -17.0
    },
    "emily engstler": {
      "minutes": 29.0,
      "points": 12.0,
      "rebounds": 8.0,
      "assists": 1.0,
      "turnovers": 0.0,
      "steals": 1.0,
      "blocks": 2.0,
      "offensiverebounds": 4.0,
      "defensiverebounds": 4.0,
      "fouls": 3.0,
      "plusminus": -9.0
    },
    "nyadiew puoch": {
      "minutes": 13.0,
      "points": 0.0,
      "rebounds": 2.0,
      "assists": 0.0,
      "turnovers": 1.0,
      "steals": 0.0,
      "blocks": 0.0,
      "offensiverebounds": 1.0,
      "defensiverebounds": 1.0,
      "fouls": 1.0,
      "plusminus": -3.0
    },
    "megan gustafson": {
      "minutes": 24.0,
      "points": 13.0,
      "rebounds": 8.0,
      "assists": 2.0,
      "turnovers": 2.0,
      "steals": 0.0,
      "blocks": 0.0,
      "offensiverebounds": 1.0,
      "defensiverebounds": 7.0,
      "fouls": 3.0,
      "plusminus": -8.0
    },
    "carla leite": {
      "minutes": 24.0,
      "points": 10.0,
      "rebounds": 1.0,
      "assists": 7.0,
      "turnovers": 4.0,
      "steals": 0.0,
      "blocks": 0.0,
      "offensiverebounds": 0.0,
      "defensiverebounds": 1.0,
      "fouls": 2.0,
      "plusminus": -3.0
    },
    "frieda buhner": {
      "minutes": 10.0,
      "points": 0.0,
      "rebounds": 0.0,
      "assists": 1.0,
      "turnovers": 1.0,
      "steals": 0.0,
      "blocks": 0.0,
      "offensiverebounds": 0.0,
      "defensiverebounds": 0.0,
      "fouls": 0.0,
      "plusminus": -9.0
    },
    "luisa geiselsoder": {
      "minutes": 11.0,
      "points": 3.0,
      "rebounds": 0.0,
      "assists": 0.0,
      "turnovers": 1.0,
      "steals": 0.0,
      "blocks": 0.0,
      "offensiverebounds": 0.0,
      "defensiverebounds": 0.0,
      "fouls": 1.0,
      "plusminus": -14.0
    },
    "serah williams": {
      "minutes": 9.0,
      "points": 7.0,
      "rebounds": 1.0,
      "assists": 0.0,
      "turnovers": 0.0,
      "steals": 0.0,
      "blocks": 0.0,
      "offensiverebounds": 0.0,
      "defensiverebounds": 1.0,
      "fouls": 1.0,
      "plusminus": 1.0
    },
    "karlie samuelson": {
      "minutes": 12.0,
      "points": 2.0,
      "rebounds": 0.0,
      "assists": 1.0,
      "turnovers": 1.0,
      "steals": 0.0,
      "blocks": 0.0,
      "offensiverebounds": 0.0,
      "defensiverebounds": 0.0,
      "fouls": 2.0,
      "plusminus": 3.0
    },
    "holly winterburn": {
      "minutes": 4.0,
      "points": 0.0,
      "rebounds": 1.0,
      "assists": 1.0,
      "turnovers": 0.0,
      "steals": 0.0,
      "blocks": 0.0,
      "offensiverebounds": 0.0,
      "defensiverebounds": 1.0,
      "fouls": 0.0,
      "plusminus": -3.0
    },
    "sarah ashlee barker": {
      "minutes": 23.0,
      "points": 8.0,
      "rebounds": 3.0,
      "assists": 3.0,
      "turnovers": 2.0,
      "steals": 0.0,
      "blocks": 0.0,
      "offensiverebounds": 0.0,
      "defensiverebounds": 3.0,
      "fouls": 1.0,
      "plusminus": -16.0
    },
    "teja oblak": {
      "minutes": 12.0,
      "points": 11.0,
      "rebounds": 1.0,
      "assists": 2.0,
      "turnovers": 3.0,
      "steals": 1.0,
      "blocks": 0.0,
      "offensiverebounds": 1.0,
      "defensiverebounds": 0.0,
      "fouls": 0.0,
      "plusminus": -12.0
    },
    "chennedy carter": {
      "minutes": 9.0,
      "points": 6.0,
      "rebounds": 1.0,
      "assists": 0.0,
      "turnovers": 0.0,
      "steals": 0.0,
      "blocks": 1.0,
      "offensiverebounds": 0.0,
      "defensiverebounds": 1.0,
      "fouls": 0.0,
      "plusminus": 2.0
    }
  }
}