[
  {
    "id": "401857064",
    "uid": "s:40~l:59~e:401857064",
    "date": "2026-07-13T23:00Z",
    "name": "Los Angeles Sparks at Atlanta Dream",
    "shortName": "LA @ ATL",
    "season": {
      "year": 2026,
      "type": 2,
      "slug": "regular-season"
    },
    "competitions": [
      {
        "id": "401857064",
        "uid": "s:40~l:59~e:401857064~c:401857064",
        "date": "2026-07-13T23:00Z",
        "attendance": 0,
        "type": {
          "id": "1",
          "abbreviation": "STD"
        },
        "timeValid": true,
        "neutralSite": false,
        "conferenceCompetition": false,
        "playByPlayAvailable": false,
        "recent": false,
        "venue": {
          "id": "6282",
          "fullName": "Gateway Center",
          "address": {
            "city": "College Park",
            "state": "GA"
          },
          "indoor": true
        },
        "competitors": [
          {
            "id": "20",
            "uid": "s:40~l:59~t:20",
            "type": "team",
            "order": 0,
            "homeAway": "home",
            "team": {
              "id": "20",
              "uid": "s:40~l:59~t:20",
              "location": "Atlanta",
              "name": "Dream",
              "abbreviation": "ATL",
              "displayName": "Atlanta Dream",
              "shortDisplayName": "Dream",
              "color": "e31837",
              "alternateColor": "5091cc",
              "isActive": true,
              "venue": {
                "id": "6282"
              },
              "links": [
                {
                  "rel": [
                    "clubhouse",
                    "desktop",
                    "team"
                  ],
                  "href": "https://www.espn.com/wnba/team/_/name/atl/atlanta-dream",
                  "text": "Clubhouse",
                  "isExternal": false,
                  "isPremium": false
                },
                {
                  "rel": [
                    "clubhouse",
                    "mobile",
                    "team"
                  ],
                  "href": "https://m.espn.com/wnba/clubhouse?teamId=20",
                  "text": "Clubhouse",
                  "isExternal": false,
                  "isPremium": false
                },
                {
                  "rel": [
                    "roster",
                    "desktop",
                    "team"
                  ],
                  "href": "https://www.espn.com/wnba/team/roster/_/name/atl/atlanta-dream",
                  "text": "Roster",
                  "isExternal": false,
                  "isPremium": false
                },
                {
                  "rel": [
                    "roster",
                    "sportscenter",
                    "app",
                    "team"
                  ],
                  "href": "sportscenter://x-callback-url/showClubhouse?uid=s:40~l:59~t:20&section=roster",
                  "text": "Roster",
                  "isExternal": false,
                  "isPremium": false
                },
                {
                  "rel": [
                    "stats",
                    "desktop",
                    "team"
                  ],
                  "href": "https://www.espn.com/wnba/team/stats/_/name/atl/atlanta-dream",
                  "text": "Statistics",
                  "isExternal": false,
                  "isPremium": false
                },
                {
                  "rel": [
                    "stats",
                    "sportscenter",
                    "app",
                    "team"
                  ],
                  "href": "sportscenter://x-callback-url/showClubhouse?uid=s:40~l:59~t:20&section=stats",
                  "text": "Statistics",
                  "isExternal": false,
                  "isPremium": false
                },
                {
                  "rel": [
                    "schedule",
                    "desktop",
                    "team"
                  ],
                  "href": "https://www.espn.com/wnba/team/schedule/_/name/atl",
                  "text": "Schedule",
                  "isExternal": false,
                  "isPremium": false
                },
                {
                  "rel": [
                    "schedule",
                    "sportscenter",
                    "app",
                    "team"
                  ],
                  "href": "sportscenter://x-callback-url/showClubhouse?uid=s:40~l:59~t:20&section=scores",
                  "text": "Schedule",
                  "isExternal": false,
                  "isPremium": false
                }
              ],
              "logo": "https://a.espncdn.com/i/teamlogos/wnba/500/atl.png"
            },
            "score": "0",
            "statistics": [
              {
                "name": "rebounds",
                "abbreviation": "REB",
                "displayValue": "797",
                "rankDisplayValue": "12th"
              },
              {
                "name": "avgRebounds",
                "abbreviation": "REB",
                "displayValue": "34.7"
              },
              {
                "name": "assists",
                "abbreviation": "AST",
                "displayValue": "455",
                "rankDisplayValue": "10th"
              },
              {
                "name": "fieldGoalsAttempted",
                "abbreviation": "FGA",
                "displayValue": "1626",
                "rankDisplayValue": "Tied-5th"
              },
              {
                "name": "fieldGoalsMade",
                "abbreviation": "FGM",
                "displayValue": "701",
                "rankDisplayValue": "8th"
              },
              {
                "name": "fieldGoalPct",
                "abbreviation": "FG%",
                "displayValue": "43.1",
                "rankDisplayValue": "12th"
              },
              {
                "name": "freeThrowPct",
                "abbreviation": "FT%",
                "displayValue": "75.5",
                "rankDisplayValue": "13th"
              },
              {
                "name": "freeThrowsAttempted",
                "abbreviation": "FTA",
                "displayValue": "563",
                "rankDisplayValue": "2nd"
              },
              {
                "name": "freeThrowsMade",
                "abbreviation": "FTM",
                "displayValue": "425",
                "rankDisplayValue": "4th"
              },
              {
                "name": "points",
                "abbreviation": "PTS",
                "displayValue": "2018",
                "rankDisplayValue": "7th"
              },
              {
                "name": "threePointPct",
                "abbreviation": "3P%",
                "displayValue": "31.2",
                "rankDisplayValue": "12th"
              },
              {
                "name": "threePointFieldGoalsAttempted",
                "abbreviation": "3PA",
                "displayValue": "613",
                "rankDisplayValue": "7th"
              },
              {
                "name": "threePointFieldGoalsMade",
                "abbreviation": "3PM",
                "displayValue": "191",
                "rankDisplayValue": "Tied-10th"
              },
              {
                "name": "avgPoints",
                "abbreviation": "PTS",
                "displayValue": "87.7"
              },
              {
                "name": "avgAssists",
                "abbreviation": "AST",
                "displayValue": "19.8"
              },
              {
                "name": "threePointFieldGoalPct",
                "abbreviation": "3P%",
                "displayValue": "31.2",
                "rankDisplayValue": "Tied-1st"
              }
            ],
            "leaders": [
              {
                "name": "pointsPerGame",
                "displayName": "Points Per Game",
                "shortDisplayName": "PPG",
                "abbreviation": "PTS",
                "leaders": [
                  {
                    "displayValue": "18.7",
                    "value": 18.69565200805664,
                    "athlete": {
                      "id": "3058901",
                      "fullName": "Allisha Gray",
                      "displayName": "Allisha Gray",
                      "shortName": "A. Gray",
                      "links": [
                        {
                          "rel": [
                            "playercard",
                            "desktop",
                            "athlete"
                          ],
                          "href": "https://www.espn.com/wnba/player/_/id/3058901/allisha-gray"
                        }
                      ],
                      "headshot": "https://a.espncdn.com/i/headshots/wnba/players/full/3058901.png",
                      "jersey": "15",
                      "position": {
                        "abbreviation": "G"
                      },
                      "team": {
                        "id": "20"
                      },
                      "active": true
                    },
                    "team": {
                      "id": "20"
                    }
                  }
                ]
              },
              {
                "name": "reboundsPerGame",
                "displayName": "Rebounds Per Game",
                "shortDisplayName": "RPG",
                "abbreviation": "REB",
                "leaders": [
                  {
                    "displayValue": "11.7",
                    "value": 11.727272987365723,
                    "athlete": {
                      "id": "4433402",
                      "fullName": "Angel Reese",
                      "displayName": "Angel Reese",
                      "shortName": "A. Reese",
                      "links": [
                        {
                          "rel": [
                            "playercard",
                            "desktop",
                            "athlete"
                          ],
                          "href": "https://www.espn.com/wnba/player/_/id/4433402/angel-reese"
                        }
                      ],
                      "headshot": "https://a.espncdn.com/i/headshots/wnba/players/full/4433402.png",
                      "jersey": "5",
                      "position": {
                        "abbreviation": "F"
                      },
                      "team": {
                        "id": "20"
                      },
                      "active": true
                    },
                    "team": {
                      "id": "20"
                    }
                  }
                ]
              },
              {
                "name": "assistsPerGame",
                "displayName": "Assists Per Game",
                "shortDisplayName": "APG",
                "abbreviation": "AST",
                "leaders": [
                  {
                    "displayValue": "7.3",
                    "value": 7.304347991943359,
                    "athlete": {
                      "id": "3142250",
                      "fullName": "Jordin Canada",
                      "displayName": "Jordin Canada",
                      "shortName": "J. Canada",
                      "links": [
                        {
                          "rel": [
                            "playercard",
                            "desktop",
                            "athlete"
                          ],
                          "href": "https://www.espn.com/wnba/player/_/id/3142250/jordin-canada"
                        }
                      ],
                      "headshot": "https://a.espncdn.com/i/headshots/wnba/players/full/3142250.png",
                      "jersey": "3",
                      "position": {
                        "abbreviation": "G"
                      },
                      "team": {
                        "id": "20"
                      },
                      "active": true
                    },
                    "team": {
                      "id": "20"
                    }
                  }
                ]
              },
              {
                "name": "rating",
                "displayName": "Rating",
                "shortDisplayName": "RAT",
                "abbreviation": "RAT",
                "leaders": [
                  {
                    "displayValue": "18.5 PPG, 3.8 RPG, 3.2 APG, 2.6 SPG, 0.8 BPG",
                    "value": 30.704545974731445,
                    "athlete": {
                      "id": "4398674",
                      "fullName": "Rhyne Howard",
                      "displayName": "Rhyne Howard",
                      "shortName": "R. Howard",
                      "links": [
                        {
                          "rel": [
                            "playercard",
                            "desktop",
                            "athlete"
                          ],
                          "href": "https://www.espn.com/wnba/player/_/id/4398674/rhyne-howard"
                        }
                      ],
                      "headshot": "https://a.espncdn.com/i/headshots/wnba/players/full/4398674.png",
                      "jersey": "10",
                      "position": {
                        "abbreviation": "G"
                      },
                      "team": {
                        "id": "20"
                      },
                      "active": true
                    },
                    "team": {
                      "id": "20"
                    }
                  }
                ]
              }
            ],
            "records": [
              {
                "name": "overall",
                "abbreviation": "Total",
                "type": "total",
                "summary": "13-10"
              },
              {
                "name": "Home",
                "type": "home",
                "summary": "7-4"
              },
              {
                "name": "Road",
                "type": "road",
                "summary": "6-6"
              }
            ]
          },
          {
            "id": "6",
            "uid": "s:40~l:59~t:6",
            "type": "team",
            "order": 1,
            "homeAway": "away",
            "team": {
              "id": "6",
              "uid": "s:40~l:59~t:6",
              "location": "Los Angeles",
              "name": "Sparks",
              "abbreviation": "LA",
              "displayName": "Los Angeles Sparks",
              "shortDisplayName": "Sparks",
              "color": "552583",
              "alternateColor": "fdb927",
              "isActive": true,
              "venue": {
                "id": "1841"
              },
              "links": [
                {
                  "rel": [
                    "clubhouse",
                    "desktop",
                    "team"
                  ],
                  "href": "https://www.espn.com/wnba/team/_/name/la/los-angeles-sparks",
                  "text": "Clubhouse",
                  "isExternal": false,
                  "isPremium": false
                },
                {
                  "rel": [
                    "clubhouse",
                    "mobile",
                    "team"
                  ],
                  "href": "https://m.espn.com/wnba/clubhouse?teamId=6",
                  "text": "Clubhouse",
                  "isExternal": false,
                  "isPremium": false
                },
                {
                  "rel": [
                    "roster",
                    "desktop",
                    "team"
                  ],
                  "href": "https://www.espn.com/wnba/team/roster/_/name/la/los-angeles-sparks",
                  "text": "Roster",
                  "isExternal": false,
                  "isPremium": false
                },
                {
                  "rel": [
                    "roster",
                    "sportscenter",
                    "app",
                    "team"
                  ],
                  "href": "sportscenter://x-callback-url/showClubhouse?uid=s:40~l:59~t:6&section=roster",
                  "text": "Roster",
                  "isExternal": false,
                  "isPremium": false
                },
                {
                  "rel": [
                    "stats",
                    "desktop",
                    "team"
                  ],
                  "href": "https://www.espn.com/wnba/team/stats/_/name/la/los-angeles-sparks",
                  "text": "Statistics",
                  "isExternal": false,
                  "isPremium": false
                },
                {
                  "rel": [
                    "stats",
                    "sportscenter",
                    "app",
                    "team"
                  ],
                  "href": "sportscenter://x-callback-url/showClubhouse?uid=s:40~l:59~t:6&section=stats",
                  "text": "Statistics",
                  "isExternal": false,
                  "isPremium": false
                },
                {
                  "rel": [
                    "schedule",
                    "desktop",
                    "team"
                  ],
                  "href": "https://www.espn.com/wnba/team/schedule/_/name/la",
                  "text": "Schedule",
                  "isExternal": false,
                  "isPremium": false
                },
                {
                  "rel": [
                    "schedule",
                    "sportscenter",
                    "app",
                    "team"
                  ],
                  "href": "sportscenter://x-callback-url/showClubhouse?uid=s:40~l:59~t:6&section=scores",
                  "text": "Schedule",
                  "isExternal": false,
                  "isPremium": false
                }
              ],
              "logo": "https://a.espncdn.com/i/teamlogos/wnba/500/la.png"
            },
            "score": "0",
            "statistics": [
              {
                "name": "rebounds",
                "abbreviation": "REB",
                "displayValue": "654",
                "rankDisplayValue": "30th"
              },
              {
                "name": "avgRebounds",
                "abbreviation": "REB",
                "displayValue": "31.1"
              },
              {
                "name": "assists",
                "abbreviation": "AST",
                "displayValue": "440",
                "rankDisplayValue": "12th"
              },
              {
                "name": "fieldGoalsAttempted",
                "abbreviation": "FGA",
                "displayValue": "1452",
                "rankDisplayValue": "14th"
              },
              {
                "name": "fieldGoalsMade",
                "abbreviation": "FGM",
                "displayValue": "662",
                "rankDisplayValue": "14th"
              },
              {
                "name": "fieldGoalPct",
                "abbreviation": "FG%",
                "displayValue": "45.6",
                "rankDisplayValue": "6th"
              },
              {
                "name": "freeThrowPct",
                "abbreviation": "FT%",
                "displayValue": "78.8",
                "rankDisplayValue": "8th"
              },
              {
                "name": "freeThrowsAttempted",
                "abbreviation": "FTA",
                "displayValue": "466",
                "rankDisplayValue": "11th"
              },
              {
                "name": "freeThrowsMade",
                "abbreviation": "FTM",
                "displayValue": "367",
                "rankDisplayValue": "10th"
              },
              {
                "name": "points",
                "abbreviation": "PTS",
                "displayValue": "1870",
                "rankDisplayValue": "13th"
              },
              {
                "name": "threePointPct",
                "abbreviation": "3P%",
                "displayValue": "32.1",
                "rankDisplayValue": "11th"
              },
              {
                "name": "threePointFieldGoalsAttempted",
                "abbreviation": "3PA",
                "displayValue": "558",
                "rankDisplayValue": "10th"
              },
              {
                "name": "threePointFieldGoalsMade",
                "abbreviation": "3PM",
                "displayValue": "179",
                "rankDisplayValue": "12th"
              },
              {
                "name": "avgPoints",
                "abbreviation": "PTS",
                "displayValue": "89.0"
              },
              {
                "name": "avgAssists",
                "abbreviation": "AST",
                "displayValue": "21.0"
              },
              {
                "name": "threePointFieldGoalPct",
                "abbreviation": "3P%",
                "displayValue": "32.1",
                "rankDisplayValue": "1st"
              }
            ],
            "records": [
              {
                "name": "overall",
                "abbreviation": "Total",
                "type": "total",
                "summary": "10-11"
              },
              {
                "name": "Home",
                "type": "home",
                "summary": "5-7"
              },
              {
                "name": "Road",
                "type": "road",
                "summary": "5-4"
              }
            ],
            "leaders": [
              {
                "name": "pointsPerGame",
                "displayName": "Points Per Game",
                "shortDisplayName": "PPG",
                "abbreviation": "PTS",
                "leaders": [
                  {
                    "displayValue": "16.9",
                    "value": 16.899999618530273,
                    "athlete": {
                      "id": "1068",
                      "fullName": "Nneka Ogwumike",
                      "displayName": "Nneka Ogwumike",
                      "shortName": "N. Ogwumike",
                      "links": [
                        {
                          "rel": [
                            "playercard",
                            "desktop",
                            "athlete"
                          ],
                          "href": "https://www.espn.com/wnba/player/_/id/1068/nneka-ogwumike"
                        }
                      ],
                      "headshot": "https://a.espncdn.com/i/headshots/wnba/players/full/1068.png",
                      "jersey": "30",
                      "position": {
                        "abbreviation": "F"
                      },
                      "team": {
                        "id": "6"
                      },
                      "active": true
                    },
                    "team": {
                      "id": "6"
                    }
                  }
                ]
              },
              {
                "name": "reboundsPerGame",
                "displayName": "Rebounds Per Game",
                "shortDisplayName": "RPG",
                "abbreviation": "REB",
                "leaders": [
                  {
                    "displayValue": "8.8",
                    "value": 8.800000190734863,
                    "athlete": {
                      "id": "1068",
                      "fullName": "Nneka Ogwumike",
                      "displayName": "Nneka Ogwumike",
                      "shortName": "N. Ogwumike",
                      "links": [
                        {
                          "rel": [
                            "playercard",
                            "desktop",
                            "athlete"
                          ],
                          "href": "https://www.espn.com/wnba/player/_/id/1068/nneka-ogwumike"
                        }
                      ],
                      "headshot": "https://a.espncdn.com/i/headshots/wnba/players/full/1068.png",
                      "jersey": "30",
                      "position": {
                        "abbreviation": "F"
                      },
                      "team": {
                        "id": "6"
                      },
                      "active": true
                    },
                    "team": {
                      "id": "6"
                    }
                  }
                ]
              },
              {
                "name": "assistsPerGame",
                "displayName": "Assists Per Game",
                "shortDisplayName": "APG",
                "abbreviation": "AST",
                "leaders": [
                  {
                    "displayValue": "5.0",
                    "value": 5.0,
                    "athlete": {
                      "id": "2491214",
                      "fullName": "Erica Wheeler",
                      "displayName": "Erica Wheeler",
                      "shortName": "E. Wheeler",
                      "links": [
                        {
                          "rel": [
                            "playercard",
                            "desktop",
                            "athlete"
                          ],
                          "href": "https://www.espn.com/wnba/player/_/id/2491214/erica-wheeler"
                        }
                      ],
                      "headshot": "https://a.espncdn.com/i/headshots/wnba/players/full/2491214.png",
                      "jersey": "17",
                      "position": {
                        "abbreviation": "G"
                      },
                      "team": {
                        "id": "6"
                      },
                      "active": true
                    },
                    "team": {
                      "id": "6"
                    }
                  }
                ]
              },
              {
                "name": "rating",
                "displayName": "Rating",
                "shortDisplayName": "RAT",
                "abbreviation": "RAT",
                "leaders": [
                  {
                    "displayValue": "16.9 PPG, 8.8 RPG, 2.6 APG, 1.1 SPG, 0.4 BPG",
                    "value": 32.68000030517578,
                    "athlete": {
                      "id": "1068",
                      "fullName": "Nneka Ogwumike",
                      "displayName": "Nneka Ogwumike",
                      "shortName": "N. Ogwumike",
                      "links": [
                        {
                          "rel": [
                            "playercard",
                            "desktop",
                            "athlete"
                          ],
                          "href": "https://www.espn.com/wnba/player/_/id/1068/nneka-ogwumike"
                        }
                      ],
                      "headshot": "https://a.espncdn.com/i/headshots/wnba/players/full/1068.png",
                      "jersey": "30",
                      "position": {
                        "abbreviation": "F"
                      },
                      "team": {
                        "id": "6"
                      },
                      "active": true
                    },
                    "team": {
                      "id": "6"
                    }
                  }
                ]
              }
            ]
          }
        ],
        "notes": [],
        "status": {
          "clock": 0.0,
          "displayClock": "0.0",
          "period": 0,
          "type": {
            "id": "1",
            "name": "STATUS_SCHEDULED",
            "state": "pre",
            "completed": false,
            "description": "Scheduled",
            "detail": "Mon, July 13th at 7:00 PM EDT",
            "shortDetail": "7/13 - 7:00 PM EDT"
          }
        },
        "broadcasts": [
          {
            "market": "national",
            "names": [
              "USA Net"
            ]
          },
          {
            "market": "home",
            "names": [
              "Atlanta News First",
              "Victory+ ATL"
            ]
          },
          {
            "market": "away",
            "names": [
              "Spectrum Sports Net"
            ]
          }
        ],
        "format": {
          "regulation": {
            "periods": 4
          }
        },
        "tickets": [
          {
            "summary": "Tickets as low as $81",
            "numberAvailable": 289,
            "links": [
              {
                "href": "https://www.vividseats.com/atlanta-dream-tickets-gateway-center-arena-at-college-park-7-13-2026--sports-wnba/production/6559164?wsUser=717"
              },
              {
                "href": "https://www.vividseats.com/venues/gateway-center-arena-at-college-park-tickets.html?wsUser=717"
              }
            ]
          }
        ],
        "startDate": "2026-07-13T23:00Z",
        "broadcast": "USA Net",
        "geoBroadcasts": [
          {
            "type": {
              "id": "1",
              "shortName": "TV"
            },
            "market": {
              "id": "1",
              "type": "National"
            },
            "media": {
              "shortName": "USA Net"
            },
            "lang": "en",
            "region": "us"
          },
          {
            "type": {
              "id": "1",
              "shortName": "TV"
            },
            "market": {
              "id": "2",
              "type": "Home"
            },
            "media": {
              "shortName": "Atlanta News First"
            },
            "lang": "en",
            "region": "us"
          },
          {
            "type": {
              "id": "1",
              "shortName": "TV"
            },
            "market": {
              "id": "3",
              "type": "Away"
            },
            "media": {
              "shortName": "Spectrum Sports Net"
            },
            "lang": "en",
            "region": "us"
          },
          {
            "type": {
              "id": "4",
              "shortName": "Streaming"
            },
            "market": {
              "id": "2",
              "type": "Home"
            },
            "media": {
              "shortName": "Victory+ ATL"
            },
            "lang": "en",
            "region": "us"
          }
        ],
        "odds": [
          {
            "provider": {
              "id": "100",
              "name": "DraftKings",
              "priority": 1,
              "logos": [
                {
                  "href": "https://a.espncdn.com/i/betting/Draftkings_Light.svg",
                  "rel": [
                    "light"
                  ]
                },
                {
                  "href": "https://a.espncdn.com/i/betting/Draftkings_Dark.svg",
                  "rel": [
                    "dark"
                  ]
                }
              ],
              "displayName": "DraftKings"
            },
            "details": "ATL -8.5",
            "overUnder": 180.5,
            "spread": -8.5,
            "awayTeamOdds": {
              "favorite": false,
              "underdog": true,
              "team": {
                "id": "6",
                "uid": "s:40~l:59~t:6",
                "abbreviation": "LA",
                "name": "Sparks",
                "displayName": "Los Angeles Sparks",
                "logo": "https://a.espncdn.com/i/teamlogos/wnba/500/la.png"
              },
              "favoriteAtOpen": false
            },
            "homeTeamOdds": {
              "favorite": true,
              "underdog": false,
              "team": {
                "id": "20",
                "uid": "s:40~l:59~t:20",
                "abbreviation": "ATL",
                "name": "Dream",
                "displayName": "Atlanta Dream",
                "logo": "https://a.espncdn.com/i/teamlogos/wnba/500/atl.png"
              },
              "favoriteAtOpen": true
            },
            "moneyline": {
              "displayName": "Moneyline",
              "shortDisplayName": "ML",
              "home": {
                "close": {
                  "odds": "-355",
                  "link": {
                    "language": "en-US",
                    "rel": [
                      "home",
                      "desktop",
                      "bets",
                      "draftkings"
                    ],
                    "href": "https://sportsbook.draftkings.com/gateway?s=__s__&wpcid=__wpcid__&wpsrc=413&wpcn=ESPN&wpscn=Widget&wpcrn=BetSlipDeepLink&wpscid=__wpscid__&wpcrid=xx&preurl=https%3A%2F%2Fsportsbook.draftkings.com%2Fevent%2F34379874%3Foutcomes%3D0ML85454105_1",
                    "text": "Home Bet",
                    "shortText": "Home Bet",
                    "isExternal": true,
                    "isPremium": false,
                    "tracking": {
                      "campaign": "betting-integrations",
                      "tags": {
                        "league": "wnba",
                        "sport": "basketball",
                        "gameId": 401857064,
                        "betSide": "home",
                        "betType": "straight"
                      }
                    }
                  }
                },
                "open": {
                  "odds": "-325"
                }
              },
              "away": {
                "close": {
                  "odds": "+280",
                  "link": {
                    "language": "en-US",
                    "rel": [
                      "away",
                      "desktop",
                      "bets",
                      "draftkings"
                    ],
                    "href": "https://sportsbook.draftkings.com/gateway?s=__s__&wpcid=__wpcid__&wpsrc=413&wpcn=ESPN&wpscn=Widget&wpcrn=BetSlipDeepLink&wpscid=__wpscid__&wpcrid=xx&preurl=https%3A%2F%2Fsportsbook.draftkings.com%2Fevent%2F34379874%3Foutcomes%3D0ML85454105_3",
                    "text": "Away Bet",
                    "shortText": "Away Bet",
                    "isExternal": true,
                    "isPremium": false,
                    "tracking": {
                      "campaign": "betting-integrations",
                      "tags": {
                        "league": "wnba",
                        "sport": "basketball",
                        "gameId": 401857064,
                        "betSide": "away",
                        "betType": "straight"
                      }
                    }
                  }
                },
                "open": {
                  "odds": "+260"
                }
              }
            },
            "pointSpread": {
              "displayName": "Spread",
              "shortDisplayName": "Spread",
              "home": {
                "close": {
                  "line": "-8.5",
                  "odds": "-102",
                  "link": {
                    "language": "en-US",
                    "rel": [
                      "homeSpread",
                      "desktop",
                      "bets"
                    ],
                    "href": "https://sportsbook.draftkings.com/gateway?s=__s__&wpcid=__wpcid__&wpsrc=413&wpcn=ESPN&wpscn=Widget&wpcrn=BetSlipDeepLink&wpscid=__wpscid__&wpcrid=xx&preurl=https%3A%2F%2Fsportsbook.draftkings.com%2Fevent%2F34379874%3Foutcomes%3D0HC85454105N850_1",
                    "text": "Home Point Spread",
                    "shortText": "Home Point Spread",
                    "isExternal": true,
                    "isPremium": false,
                    "tracking": {
                      "campaign": "betting-integrations",
                      "tags": {
                        "league": "wnba",
                        "sport": "basketball",
                        "gameId": 401857064,
                        "betSide": "none",
                        "betType": "straight",
                        "betDetails": "Spread:ATL-8.5"
                      }
                    }
                  }
                },
                "open": {
                  "line": "-7.5",
                  "odds": "-110"
                }
              },
              "away": {
                "close": {
                  "line": "+8.5",
                  "odds": "-118",
                  "link": {
                    "language": "en-US",
                    "rel": [
                      "awaySpread",
                      "desktop",
                      "bets"
                    ],
                    "href": "https://sportsbook.draftkings.com/gateway?s=__s__&wpcid=__wpcid__&wpsrc=413&wpcn=ESPN&wpscn=Widget&wpcrn=BetSlipDeepLink&wpscid=__wpscid__&wpcrid=xx&preurl=https%3A%2F%2Fsportsbook.draftkings.com%2Fevent%2F34379874%3Foutcomes%3D0HC85454105P850_3",
                    "text": "Away Point Spread",
                    "shortText": "Away Point Spread",
                    "isExternal": true,
                    "isPremium": false,
                    "tracking": {
                      "campaign": "betting-integrations",
                      "tags": {
                        "league": "wnba",
                        "sport": "basketball",
                        "gameId": 401857064,
                        "betSide": "none",
                        "betType": "straight",
                        "betDetails": "Spread:LA+8.5"
                      }
                    }
                  }
                },
                "open": {
                  "line": "+7.5",
                  "odds": "-110"
                }
              }
            },
            "total": {
              "displayName": "Total",
              "shortDisplayName": "Total",
              "over": {
                "close": {
                  "line": "o180.5",
                  "odds": "-108",
                  "link": {
                    "language": "en-US",
                    "rel": [
                      "over",
                      "desktop",
                      "bets"
                    ],
                    "href": "https://sportsbook.draftkings.com/gateway?s=__s__&wpcid=__wpcid__&wpsrc=413&wpcn=ESPN&wpscn=Widget&wpcrn=BetSlipDeepLink&wpscid=__wpscid__&wpcrid=xx&preurl=https%3A%2F%2Fsportsbook.draftkings.com%2Fevent%2F34379874%3Foutcomes%3D0OU85454105O18050_1",
                    "text": "Over Odds",
                    "shortText": "Over Odds",
                    "isExternal": true,
                    "isPremium": false,
                    "tracking": {
                      "campaign": "betting-integrations",
                      "tags": {
                        "league": "wnba",
                        "sport": "basketball",
                        "gameId": 401857064,
                        "betSide": "over",
                        "betType": "straight",
                        "betDetails": "Over:180.5"
                      }
                    }
                  }
                },
                "open": {
                  "line": "o177.5",
                  "odds": "-110"
                }
              },
              "under": {
                "close": {
                  "line": "u180.5",
                  "odds": "-112",
                  "link": {
                    "language": "en-US",
                    "rel": [
                      "under",
                      "desktop",
                      "bets"
                    ],
                    "href": "https://sportsbook.draftkings.com/gateway?s=__s__&wpcid=__wpcid__&wpsrc=413&wpcn=ESPN&wpscn=Widget&wpcrn=BetSlipDeepLink&wpscid=__wpscid__&wpcrid=xx&preurl=https%3A%2F%2Fsportsbook.draftkings.com%2Fevent%2F34379874%3Foutcomes%3D0OU85454105U18050_3",
                    "text": "Under Odds",
                    "shortText": "Under Odds",
                    "isExternal": true,
                    "isPremium": false,
                    "tracking": {
                      "campaign": "betting-integrations",
                      "tags": {
                        "league": "wnba",
                        "sport": "basketball",
                        "gameId": 401857064,
                        "betSide": "under",
                        "betType": "straight",
                        "betDetails": "Under:180.5"
                      }
                    }
                  }
                },
                "open": {
                  "line": "u177.5",
                  "odds": "-110"
                }
              }
            },
            "link": {
              "language": "en-US",
              "rel": [
                "game",
                "desktop",
                "bets"
              ],
              "href": "https://sportsbook.draftkings.com/gateway?s=__s__&wpcid=__wpcid__&wpsrc=413&wpcn=ESPN&wpscn=Widget&wpcrn=BetSlipDeepLink&wpscid=__wpscid__&wpcrid=xx&preurl=https%3A%2F%2Fsportsbook.draftkings.com%2Fevent%2F34379874",
              "text": "See More Odds",
              "shortText": "Game",
              "isExternal": true,
              "isPremium": false,
              "tracking": {
                "campaign": "betting-integrations",
                "tags": {
                  "league": "wnba",
                  "sport": "basketball",
                  "gameId": 401857064,
                  "betSide": "none",
                  "betType": "straight"
                }
              }
            },
            "header": {
              "logo": {
                "dark": "https://a.espncdn.com/i/espnbet/dark/espn-bet-square-off.svg",
                "light": "https://a.espncdn.com/i/espnbet/espn-bet-square-off.svg",
                "exclusivesLogoDark": "https://a.espncdn.com/i/espnbet/espn-bet-square-mint.svg",
                "exclusivesLogoLight": "https://a.espncdn.com/i/espnbet/espn-bet-square-mint.svg"
              },
              "text": "Game Odds"
            },
            "footer": {
              "disclaimer": "GAMBLING PROBLEM? CALL 1-800-GAMBLER or 1-800-MY-RESET, (800) 327-5050 or visit gamblinghelplinema.org (MA). Call 877-8-HOPENY/text HOPENY (467369) (NY). Call 888-789-7777/visit ccpg.org (CT), or visit www.mdgamblinghelp.org (MD), 1-800-981-0023 (PR). 21+ and present in most states. (18+ DC/KY/NH/PR/WY). Void in ONT. Eligibility restrictions apply. Terms: draftkings.com/sportsbook. On behalf of Boot Hill Casino (KS). Pass-thru of per wager tax may apply in IL."
            }
          }
        ],
        "highlights": []
      }
    ],
    "links": [
      {
        "language": "en-US",
        "rel": [
          "summary",
          "desktop",
          "event"
        ],
        "href": "https://www.espn.com/wnba/game/_/gameId/401857064/sparks-dream",
        "text": "Gamecast",
        "shortText": "Gamecast",
        "isExternal": false,
        "isPremium": false
      }
    ],
    "status": {
      "clock": 0.0,
      "displayClock": "0.0",
      "period": 0,
      "type": {
        "id": "1",
        "name": "STATUS_SCHEDULED",
        "state": "pre",
        "completed": false,
        "description": "Scheduled",
        "detail": "Mon, July 13th at 7:00 PM EDT",
        "shortDetail": "7/13 - 7:00 PM EDT"
      }
    }
  },
  {
    "id": "401857065",
    "uid": "s:40~l:59~e:401857065",
    "date": "2026-07-14T01:00Z",
    "name": "Phoenix Mercury at Minnesota Lynx",
    "shortName": "PHX @ MIN",
    "season": {
      "year": 2026,
      "type": 2,
      "slug": "regular-season"
    },
    "competitions": [
      {
        "id": "401857065",
        "uid": "s:40~l:59~e:401857065~c:401857065",
        "date": "2026-07-14T01:00Z",
        "attendance": 0,
        "type": {
          "id": "1",
          "abbreviation": "STD"
        },
        "timeValid": true,
        "neutralSite": false,
        "conferenceCompetition": false,
        "playByPlayAvailable": false,
        "recent": false,
        "venue": {
          "id": "2029",
          "fullName": "Target Center",
          "address": {
            "city": "Minneapolis",
            "state": "MN"
          },
          "indoor": true
        },
        "competitors": [
          {
            "id": "8",
            "uid": "s:40~l:59~t:8",
            "type": "team",
            "order": 0,
            "homeAway": "home",
            "team": {
              "id": "8",
              "uid": "s:40~l:59~t:8",
              "location": "Minnesota",
              "name": "Lynx",
              "abbreviation": "MIN",
              "displayName": "Minnesota Lynx",
              "shortDisplayName": "Lynx",
              "color": "266092",
              "alternateColor": "79bc43",
              "isActive": true,
              "venue": {
                "id": "2029"
              },
              "links": [
                {
                  "rel": [
                    "clubhouse",
                    "desktop",
                    "team"
                  ],
                  "href": "https://www.espn.com/wnba/team/_/name/min/minnesota-lynx",
                  "text": "Clubhouse",
                  "isExternal": false,
                  "isPremium": false
                },
                {
                  "rel": [
                    "clubhouse",
                    "mobile",
                    "team"
                  ],
                  "href": "https://m.espn.com/wnba/clubhouse?teamId=8",
                  "text": "Clubhouse",
                  "isExternal": false,
                  "isPremium": false
                },
                {
                  "rel": [
                    "roster",
                    "desktop",
                    "team"
                  ],
                  "href": "https://www.espn.com/wnba/team/roster/_/name/min/minnesota-lynx",
                  "text": "Roster",
                  "isExternal": false,
                  "isPremium": false
                },
                {
                  "rel": [
                    "roster",
                    "sportscenter",
                    "app",
                    "team"
                  ],
                  "href": "sportscenter://x-callback-url/showClubhouse?uid=s:40~l:59~t:8&section=roster",
                  "text": "Roster",
                  "isExternal": false,
                  "isPremium": false
                },
                {
                  "rel": [
                    "stats",
                    "desktop",
                    "team"
                  ],
                  "href": "https://www.espn.com/wnba/team/stats/_/name/min/minnesota-lynx",
                  "text": "Statistics",
                  "isExternal": false,
                  "isPremium": false
                },
                {
                  "rel": [
                    "stats",
                    "sportscenter",
                    "app",
                    "team"
                  ],
                  "href": "sportscenter://x-callback-url/showClubhouse?uid=s:40~l:59~t:8&section=stats",
                  "text": "Statistics",
                  "isExternal": false,
                  "isPremium": false
                },
                {
                  "rel": [
                    "schedule",
                    "desktop",
                    "team"
                  ],
                  "href": "https://www.espn.com/wnba/team/schedule/_/name/min",
                  "text": "Schedule",
                  "isExternal": false,
                  "isPremium": false
                },
                {
                  "rel": [
                    "schedule",
                    "sportscenter",
                    "app",
                    "team"
                  ],
                  "href": "sportscenter://x-callback-url/showClubhouse?uid=s:40~l:59~t:8&section=scores",
                  "text": "Schedule",
                  "isExternal": false,
                  "isPremium": false
                }
              ],
              "logo": "https://a.espncdn.com/i/teamlogos/wnba/500/min.png"
            },
            "score": "0",
            "statistics": [
              {
                "name": "rebounds",
                "abbreviation": "REB",
                "displayValue": "839",
                "rankDisplayValue": "6th"
              },
              {
                "name": "avgRebounds",
                "abbreviation": "REB",
                "displayValue": "36.5"
              },
              {
                "name": "assists",
                "abbreviation": "AST",
                "displayValue": "490",
                "rankDisplayValue": "4th"
              },
              {
                "name": "fieldGoalsAttempted",
                "abbreviation": "FGA",
                "displayValue": "1626",
                "rankDisplayValue": "Tied-5th"
              },
              {
                "name": "fieldGoalsMade",
                "abbreviation": "FGM",
                "displayValue": "776",
                "rankDisplayValue": "3rd"
              },
              {
                "name": "fieldGoalPct",
                "abbreviation": "FG%",
                "displayValue": "47.7",
                "rankDisplayValue": "2nd"
              },
              {
                "name": "freeThrowPct",
                "abbreviation": "FT%",
                "displayValue": "79.4",
                "rankDisplayValue": "7th"
              },
              {
                "name": "freeThrowsAttempted",
                "abbreviation": "FTA",
                "displayValue": "412",
                "rankDisplayValue": "15th"
              },
              {
                "name": "freeThrowsMade",
                "abbreviation": "FTM",
                "displayValue": "327",
                "rankDisplayValue": "15th"
              },
              {
                "name": "points",
                "abbreviation": "PTS",
                "displayValue": "2070",
                "rankDisplayValue": "5th"
              },
              {
                "name": "threePointPct",
                "abbreviation": "3P%",
                "displayValue": "37.7",
                "rankDisplayValue": "1st"
              },
              {
                "name": "threePointFieldGoalsAttempted",
                "abbreviation": "3PA",
                "displayValue": "506",
                "rankDisplayValue": "13th"
              },
              {
                "name": "threePointFieldGoalsMade",
                "abbreviation": "3PM",
                "displayValue": "191",
                "rankDisplayValue": "Tied-10th"
              },
              {
                "name": "avgPoints",
                "abbreviation": "PTS",
                "displayValue": "90.0"
              },
              {
                "name": "avgAssists",
                "abbreviation": "AST",
                "displayValue": "21.3"
              },
              {
                "name": "threePointFieldGoalPct",
                "abbreviation": "3P%",
                "displayValue": "37.7"
              }
            ],
            "records": [
              {
                "name": "overall",
                "abbreviation": "Total",
                "type": "total",
                "summary": "17-6"
              },
              {
                "name": "Home",
                "type": "home",
                "summary": "7-4"
              },
              {
                "name": "Road",
                "type": "road",
                "summary": "10-2"
              }
            ],
            "leaders": [
              {
                "name": "pointsPerGame",
                "displayName": "Points Per Game",
                "shortDisplayName": "PPG",
                "abbreviation": "PTS",
                "leaders": [
                  {
                    "displayValue": "18.7",
                    "value": 18.714284896850586,
                    "athlete": {
                      "id": "4433791",
                      "fullName": "Olivia Miles",
                      "displayName": "Olivia Miles",
                      "shortName": "O. Miles",
                      "links": [
                        {
                          "rel": [
                            "playercard",
                            "desktop",
                            "athlete"
                          ],
                          "href": "https://www.espn.com/wnba/player/_/id/4433791/olivia-miles"
                        }
                      ],
                      "headshot": "https://a.espncdn.com/i/headshots/wnba/players/full/4433791.png",
                      "jersey": "5",
                      "position": {
                        "abbreviation": "G"
                      },
                      "team": {
                        "id": "8"
                      },
                      "active": true
                    },
                    "team": {
                      "id": "8"
                    }
                  }
                ]
              },
              {
                "name": "reboundsPerGame",
                "displayName": "Rebounds Per Game",
                "shortDisplayName": "RPG",
                "abbreviation": "REB",
                "leaders": [
                  {
                    "displayValue": "8.1",
                    "value": 8.086956977844238,
                    "athlete": {
                      "id": "2529130",
                      "fullName": "Natasha Howard",
                      "displayName": "Natasha Howard",
                      "shortName": "N. Howard",
                      "links": [
                        {
                          "rel": [
                            "playercard",
                            "desktop",
                            "athlete"
                          ],
                          "href": "https://www.espn.com/wnba/player/_/id/2529130/natasha-howard"
                        }
                      ],
                      "headshot": "https://a.espncdn.com/i/headshots/wnba/players/full/2529130.png",
                      "jersey": "1",
                      "position": {
                        "abbreviation": "F"
                      },
                      "team": {
                        "id": "8"
                      },
                      "active": true
                    },
                    "team": {
                      "id": "8"
                    }
                  }
                ]
              },
              {
                "name": "assistsPerGame",
                "displayName": "Assists Per Game",
                "shortDisplayName": "APG",
                "abbreviation": "AST",
                "leaders": [
                  {
                    "displayValue": "5.6",
                    "value": 5.61904764175415,
                    "athlete": {
                      "id": "4433791",
                      "fullName": "Olivia Miles",
                      "displayName": "Olivia Miles",
                      "shortName": "O. Miles",
                      "links": [
                        {
                          "rel": [
                            "playercard",
                            "desktop",
                            "athlete"
                          ],
                          "href": "https://www.espn.com/wnba/player/_/id/4433791/olivia-miles"
                        }
                      ],
                      "headshot": "https://a.espncdn.com/i/headshots/wnba/players/full/4433791.png",
                      "jersey": "5",
                      "position": {
                        "abbreviation": "G"
                      },
                      "team": {
                        "id": "8"
                      },
                      "active": true
                    },
                    "team": {
                      "id": "8"
                    }
                  }
                ]
              },
              {
                "name": "rating",
                "displayName": "Rating",
                "shortDisplayName": "RAT",
                "abbreviation": "RAT",
                "leaders": [
                  {
                    "displayValue": "18.7 PPG, 4.8 RPG, 5.6 APG, 1.3 SPG, 0.8 BPG",
                    "value": 33.990474700927734,
                    "athlete": {
                      "id": "4433791",
                      "fullName": "Olivia Miles",
                      "displayName": "Olivia Miles",
                      "shortName": "O. Miles",
                      "links": [
                        {
                          "rel": [
                            "playercard",
                            "desktop",
                            "athlete"
                          ],
                          "href": "https://www.espn.com/wnba/player/_/id/4433791/olivia-miles"
                        }
                      ],
                      "headshot": "https://a.espncdn.com/i/headshots/wnba/players/full/4433791.png",
                      "jersey": "5",
                      "position": {
                        "abbreviation": "G"
                      },
                      "team": {
                        "id": "8"
                      },
                      "active": true
                    },
                    "team": {
                      "id": "8"
                    }
                  }
                ]
              }
            ]
          },
          {
            "id": "11",
            "uid": "s:40~l:59~t:11",
            "type": "team",
            "order": 1,
            "homeAway": "away",
            "team": {
              "id": "11",
              "uid": "s:40~l:59~t:11",
              "location": "Phoenix",
              "name": "Mercury",
              "abbreviation": "PHX",
              "displayName": "Phoenix Mercury",
              "shortDisplayName": "Mercury",
              "color": "3c286e",
              "alternateColor": "fa4b0a",
              "isActive": true,
              "venue": {
                "id": "1949"
              },
              "links": [
                {
                  "rel": [
                    "clubhouse",
                    "desktop",
                    "team"
                  ],
                  "href": "https://www.espn.com/wnba/team/_/name/phx/phoenix-mercury",
                  "text": "Clubhouse",
                  "isExternal": false,
                  "isPremium": false
                },
                {
                  "rel": [
                    "clubhouse",
                    "mobile",
                    "team"
                  ],
                  "href": "https://m.espn.com/wnba/clubhouse?teamId=11",
                  "text": "Clubhouse",
                  "isExternal": false,
                  "isPremium": false
                },
                {
                  "rel": [
                    "roster",
                    "desktop",
                    "team"
                  ],
                  "href": "https://www.espn.com/wnba/team/roster/_/name/phx/phoenix-mercury",
                  "text": "Roster",
                  "isExternal": false,
                  "isPremium": false
                },
                {
                  "rel": [
                    "roster",
                    "sportscenter",
                    "app",
                    "team"
                  ],
                  "href": "sportscenter://x-callback-url/showClubhouse?uid=s:40~l:59~t:11&section=roster",
                  "text": "Roster",
                  "isExternal": false,
                  "isPremium": false
                },
                {
                  "rel": [
                    "stats",
                    "desktop",
                    "team"
                  ],
                  "href": "https://www.espn.com/wnba/team/stats/_/name/phx/phoenix-mercury",
                  "text": "Statistics",
                  "isExternal": false,
                  "isPremium": false
                },
                {
                  "rel": [
                    "stats",
                    "sportscenter",
                    "app",
                    "team"
                  ],
                  "href": "sportscenter://x-callback-url/showClubhouse?uid=s:40~l:59~t:11&section=stats",
                  "text": "Statistics",
                  "isExternal": false,
                  "isPremium": false
                },
                {
                  "rel": [
                    "schedule",
                    "desktop",
                    "team"
                  ],
                  "href": "https://www.espn.com/wnba/team/schedule/_/name/phx",
                  "text": "Schedule",
                  "isExternal": false,
                  "isPremium": false
                },
                {
                  "rel": [
                    "schedule",
                    "sportscenter",
                    "app",
                    "team"
                  ],
                  "href": "sportscenter://x-callback-url/showClubhouse?uid=s:40~l:59~t:11&section=scores",
                  "text": "Schedule",
                  "isExternal": false,
                  "isPremium": false
                }
              ],
              "logo": "https://a.espncdn.com/i/teamlogos/wnba/500/scoreboard/phx.png"
            },
            "score": "0",
            "statistics": [
              {
                "name": "rebounds",
                "abbreviation": "REB",
                "displayValue": "764",
                "rankDisplayValue": "Tied-5th"
              },
              {
                "name": "avgRebounds",
                "abbreviation": "REB",
                "displayValue": "31.8"
              },
              {
                "name": "assists",
                "abbreviation": "AST",
                "displayValue": "454",
                "rankDisplayValue": "11th"
              },
              {
                "name": "fieldGoalsAttempted",
                "abbreviation": "FGA",
                "displayValue": "1574",
                "rankDisplayValue": "9th"
              },
              {
                "name": "fieldGoalsMade",
                "abbreviation": "FGM",
                "displayValue": "682",
                "rankDisplayValue": "11th"
              },
              {
                "name": "fieldGoalPct",
                "abbreviation": "FG%",
                "displayValue": "43.3",
                "rankDisplayValue": "11th"
              },
              {
                "name": "freeThrowPct",
                "abbreviation": "FT%",
                "displayValue": "78.7",
                "rankDisplayValue": "9th"
              },
              {
                "name": "freeThrowsAttempted",
                "abbreviation": "FTA",
                "displayValue": "539",
                "rankDisplayValue": "4th"
              },
              {
                "name": "freeThrowsMade",
                "abbreviation": "FTM",
                "displayValue": "424",
                "rankDisplayValue": "5th"
              },
              {
                "name": "points",
                "abbreviation": "PTS",
                "displayValue": "1982",
                "rankDisplayValue": "10th"
              },
              {
                "name": "threePointPct",
                "abbreviation": "3P%",
                "displayValue": "32.6",
                "rankDisplayValue": "10th"
              },
              {
                "name": "threePointFieldGoalsAttempted",
                "abbreviation": "3PA",
                "displayValue": "596",
                "rankDisplayValue": "8th"
              },
              {
                "name": "threePointFieldGoalsMade",
                "abbreviation": "3PM",
                "displayValue": "194",
                "rankDisplayValue": "9th"
              },
              {
                "name": "avgPoints",
                "abbreviation": "PTS",
                "displayValue": "82.6"
              },
              {
                "name": "avgAssists",
                "abbreviation": "AST",
                "displayValue": "18.9"
              },
              {
                "name": "threePointFieldGoalPct",
                "abbreviation": "3P%",
                "displayValue": "32.6",
                "rankDisplayValue": "1st"
              }
            ],
            "records": [
              {
                "name": "overall",
                "abbreviation": "Total",
                "type": "total",
                "summary": "8-16"
              },
              {
                "name": "Home",
                "type": "home",
                "summary": "3-8"
              },
              {
                "name": "Road",
                "type": "road",
                "summary": "5-8"
              }
            ],
            "leaders": [
              {
                "name": "pointsPerGame",
                "displayName": "Points Per Game",
                "shortDisplayName": "PPG",
                "abbreviation": "PTS",
                "leaders": [
                  {
                    "displayValue": "20.3",
                    "value": 20.30434799194336,
                    "athlete": {
                      "id": "2998938",
                      "fullName": "Kahleah Copper",
                      "displayName": "Kahleah Copper",
                      "shortName": "K. Copper",
                      "links": [
                        {
                          "rel": [
                            "playercard",
                            "desktop",
                            "athlete"
                          ],
                          "href": "https://www.espn.com/wnba/player/_/id/2998938/kahleah-copper"
                        }
                      ],
                      "headshot": "https://a.espncdn.com/i/headshots/wnba/players/full/2998938.png",
                      "jersey": "2",
                      "position": {
                        "abbreviation": "G"
                      },
                      "team": {
                        "id": "11"
                      },
                      "active": true
                    },
                    "team": {
                      "id": "11"
                    }
                  }
                ]
              },
              {
                "name": "reboundsPerGame",
                "displayName": "Rebounds Per Game",
                "shortDisplayName": "RPG",
                "abbreviation": "REB",
                "leaders": [
                  {
                    "displayValue": "6.8",
                    "value": 6.818181991577148,
                    "athlete": {
                      "id": "2529140",
                      "fullName": "Alyssa Thomas",
                      "displayName": "Alyssa Thomas",
                      "shortName": "A. Thomas",
                      "links": [
                        {
                          "rel": [
                            "playercard",
                            "desktop",
                            "athlete"
                          ],
                          "href": "https://www.espn.com/wnba/player/_/id/2529140/alyssa-thomas"
                        }
                      ],
                      "headshot": "https://a.espncdn.com/i/headshots/wnba/players/full/2529140.png",
                      "jersey": "25",
                      "position": {
                        "abbreviation": "F"
                      },
                      "team": {
                        "id": "11"
                      },
                      "active": true
                    },
                    "team": {
                      "id": "11"
                    }
                  }
                ]
              },
              {
                "name": "assistsPerGame",
                "displayName": "Assists Per Game",
                "shortDisplayName": "APG",
                "abbreviation": "AST",
                "leaders": [
                  {
                    "displayValue": "7.9",
                    "value": 7.863636493682861,
                    "athlete": {
                      "id": "2529140",
                      "fullName": "Alyssa Thomas",
                      "displayName": "Alyssa Thomas",
                      "shortName": "A. Thomas",
                      "links": [
                        {
                          "rel": [
                            "playercard",
                            "desktop",
                            "athlete"
                          ],
                          "href": "https://www.espn.com/wnba/player/_/id/2529140/alyssa-thomas"
                        }
                      ],
                      "headshot": "https://a.espncdn.com/i/headshots/wnba/players/full/2529140.png",
                      "jersey": "25",
                      "position": {
                        "abbreviation": "F"
                      },
                      "team": {
                        "id": "11"
                      },
                      "active": true
                    },
                    "team": {
                      "id": "11"
                    }
                  }
                ]
              },
              {
                "name": "rating",
                "displayName": "Rating",
                "shortDisplayName": "RAT",
                "abbreviation": "RAT",
                "leaders": [
                  {
                    "displayValue": "14.2 PPG, 6.8 RPG, 7.9 APG, 1.5 SPG, 0.4 BPG",
                    "value": 32.50682067871094,
                    "athlete": {
                      "id": "2529140",
                      "fullName": "Alyssa Thomas",
                      "displayName": "Alyssa Thomas",
                      "shortName": "A. Thomas",
                      "links": [
                        {
                          "rel": [
                            "playercard",
                            "desktop",
                            "athlete"
                          ],
                          "href": "https://www.espn.com/wnba/player/_/id/2529140/alyssa-thomas"
                        }
                      ],
                      "headshot": "https://a.espncdn.com/i/headshots/wnba/players/full/2529140.png",
                      "jersey": "25",
                      "position": {
                        "abbreviation": "F"
                      },
                      "team": {
                        "id": "11"
                      },
                      "active": true
                    },
                    "team": {
                      "id": "11"
                    }
                  }
                ]
              }
            ]
          }
        ],
        "notes": [],
        "status": {
          "clock": 0.0,
          "displayClock": "0.0",
          "period": 0,
          "type": {
            "id": "1",
            "name": "STATUS_SCHEDULED",
            "state": "pre",
            "completed": false,
            "description": "Scheduled",
            "detail": "Mon, July 13th at 9:00 PM EDT",
            "shortDetail": "7/13 - 9:00 PM EDT"
          }
        },
        "broadcasts": [
          {
            "market": "national",
            "names": [
              "Peacock",
              "NBCSN"
            ]
          },
          {
            "market": "home",
            "names": [
              "Victory+ MIN"
            ]
          },
          {
            "market": "away",
            "names": [
              "Merc+",
              "Arizona's Family 3TV"
            ]
          }
        ],
        "format": {
          "regulation": {
            "periods": 4
          }
        },
        "tickets": [
          {
            "summary": "Tickets as low as $30",
            "numberAvailable": 165,
            "links": [
              {
                "href": "https://www.vividseats.com/minnesota-lynx-tickets-target-center-7-13-2026--sports-wnba/production/6559102?wsUser=717"
              },
              {
                "href": "https://www.vividseats.com/target-center-tickets/venue/1663?wsUser=717"
              }
            ]
          }
        ],
        "startDate": "2026-07-14T01:00Z",
        "broadcast": "Peacock/NBCSN",
        "geoBroadcasts": [
          {
            "type": {
              "id": "4",
              "shortName": "Streaming"
            },
            "market": {
              "id": "1",
              "type": "National"
            },
            "media": {
              "shortName": "Peacock"
            },
            "lang": "en",
            "region": "us"
          },
          {
            "type": {
              "id": "1",
              "shortName": "TV"
            },
            "market": {
              "id": "1",
              "type": "National"
            },
            "media": {
              "shortName": "NBCSN"
            },
            "lang": "en",
            "region": "us"
          },
          {
            "type": {
              "id": "4",
              "shortName": "Streaming"
            },
            "market": {
              "id": "2",
              "type": "Home"
            },
            "media": {
              "shortName": "Victory+ MIN"
            },
            "lang": "en",
            "region": "us"
          },
          {
            "type": {
              "id": "4",
              "shortName": "Streaming"
            },
            "market": {
              "id": "3",
              "type": "Away"
            },
            "media": {
              "shortName": "Merc+"
            },
            "lang": "en",
            "region": "us"
          },
          {
            "type": {
              "id": "1",
              "shortName": "TV"
            },
            "market": {
              "id": "3",
              "type": "Away"
            },
            "media": {
              "shortName": "Arizona's Family 3TV"
            },
            "lang": "en",
            "region": "us"
          }
        ],
        "odds": [
          {
            "provider": {
              "id": "100",
              "name": "DraftKings",
              "priority": 1,
              "logos": [
                {
                  "href": "https://a.espncdn.com/i/betting/Draftkings_Light.svg",
                  "rel": [
                    "light"
                  ]
                },
                {
                  "href": "https://a.espncdn.com/i/betting/Draftkings_Dark.svg",
                  "rel": [
                    "dark"
                  ]
                }
              ]
            },
            "details": "MIN -12.5",
            "overUnder": 169.5,
            "spread": -12.5,
            "awayTeamOdds": {
              "favorite": false,
              "underdog": true,
              "team": {
                "id": "11",
                "uid": "s:40~l:59~t:11",
                "abbreviation": "PHX",
                "name": "Mercury",
                "displayName": "Phoenix Mercury",
                "logo": "https://a.espncdn.com/i/teamlogos/wnba/500/scoreboard/phx.png"
              },
              "favoriteAtOpen": false
            },
            "homeTeamOdds": {
              "favorite": true,
              "underdog": false,
              "team": {
                "id": "8",
                "uid": "s:40~l:59~t:8",
                "abbreviation": "MIN",
                "name": "Lynx",
                "displayName": "Minnesota Lynx",
                "logo": "https://a.espncdn.com/i/teamlogos/wnba/500/min.png"
              },
              "favoriteAtOpen": true
            },
            "moneyline": {
              "displayName": "Moneyline",
              "shortDisplayName": "ML",
              "home": {
                "close": {
                  "odds": "-800",
                  "link": {
                    "language": "en-US",
                    "rel": [
                      "home",
                      "desktop",
                      "bets",
                      "draftkings"
                    ],
                    "href": "https://sportsbook.draftkings.com/gateway?s=__s__&wpcid=__wpcid__&wpsrc=413&wpcn=ESPN&wpscn=Widget&wpcrn=BetSlipDeepLink&wpscid=__wpscid__&wpcrid=xx&preurl=https%3A%2F%2Fsportsbook.draftkings.com%2Fevent%2F34379875%3Foutcomes%3D0ML85454106_1",
                    "text": "Home Bet",
                    "shortText": "Home Bet",
                    "isExternal": true,
                    "isPremium": false,
                    "tracking": {
                      "campaign": "betting-integrations",
                      "tags": {
                        "league": "wnba",
                        "sport": "basketball",
                        "gameId": 401857065,
                        "betSide": "home",
                        "betType": "straight"
                      }
                    }
                  }
                },
                "open": {
                  "odds": "-550"
                }
              },
              "away": {
                "close": {
                  "odds": "+550",
                  "link": {
                    "language": "en-US",
                    "rel": [
                      "away",
                      "desktop",
                      "bets",
                      "draftkings"
                    ],
                    "href": "https://sportsbook.draftkings.com/gateway?s=__s__&wpcid=__wpcid__&wpsrc=413&wpcn=ESPN&wpscn=Widget&wpcrn=BetSlipDeepLink&wpscid=__wpscid__&wpcrid=xx&preurl=https%3A%2F%2Fsportsbook.draftkings.com%2Fevent%2F34379875%3Foutcomes%3D0ML85454106_3",
                    "text": "Away Bet",
                    "shortText": "Away Bet",
                    "isExternal": true,
                    "isPremium": false,
                    "tracking": {
                      "campaign": "betting-integrations",
                      "tags": {
                        "league": "wnba",
                        "sport": "basketball",
                        "gameId": 401857065,
                        "betSide": "away",
                        "betType": "straight"
                      }
                    }
                  }
                },
                "open": {
                  "odds": "+410"
                }
              }
            },
            "pointSpread": {
              "displayName": "Spread",
              "shortDisplayName": "Spread",
              "home": {
                "close": {
                  "line": "-12.5",
                  "odds": "-118",
                  "link": {
                    "language": "en-US",
                    "rel": [
                      "homeSpread",
                      "desktop",
                      "bets"
                    ],
                    "href": "https://sportsbook.draftkings.com/gateway?s=__s__&wpcid=__wpcid__&wpsrc=413&wpcn=ESPN&wpscn=Widget&wpcrn=BetSlipDeepLink&wpscid=__wpscid__&wpcrid=xx&preurl=https%3A%2F%2Fsportsbook.draftkings.com%2Fevent%2F34379875%3Foutcomes%3D0HC85454106N1250_1",
                    "text": "Home Point Spread",
                    "shortText": "Home Point Spread",
                    "isExternal": true,
                    "isPremium": false,
                    "tracking": {
                      "campaign": "betting-integrations",
                      "tags": {
                        "league": "wnba",
                        "sport": "basketball",
                        "gameId": 401857065,
                        "betSide": "none",
                        "betType": "straight",
                        "betDetails": "Spread:MIN-12.5"
                      }
                    }
                  }
                },
                "open": {
                  "line": "-10.5",
                  "odds": "-110"
                }
              },
              "away": {
                "close": {
                  "line": "+12.5",
                  "odds": "-102",
                  "link": {
                    "language": "en-US",
                    "rel": [
                      "awaySpread",
                      "desktop",
                      "bets"
                    ],
                    "href": "https://sportsbook.draftkings.com/gateway?s=__s__&wpcid=__wpcid__&wpsrc=413&wpcn=ESPN&wpscn=Widget&wpcrn=BetSlipDeepLink&wpscid=__wpscid__&wpcrid=xx&preurl=https%3A%2F%2Fsportsbook.draftkings.com%2Fevent%2F34379875%3Foutcomes%3D0HC85454106P1250_3",
                    "text": "Away Point Spread",
                    "shortText": "Away Point Spread",
                    "isExternal": true,
                    "isPremium": false,
                    "tracking": {
                      "campaign": "betting-integrations",
                      "tags": {
                        "league": "wnba",
                        "sport": "basketball",
                        "gameId": 401857065,
                        "betSide": "none",
                        "betType": "straight",
                        "betDetails": "Spread:PHX+12.5"
                      }
                    }
                  }
                },
                "open": {
                  "line": "+10.5",
                  "odds": "-110"
                }
              }
            },
            "total": {
              "displayName": "Total",
              "shortDisplayName": "Total",
              "over": {
                "close": {
                  "line": "o169.5",
                  "odds": "-115",
                  "link": {
                    "language": "en-US",
                    "rel": [
                      "over",
                      "desktop",
                      "bets"
                    ],
                    "href": "https://sportsbook.draftkings.com/gateway?s=__s__&wpcid=__wpcid__&wpsrc=413&wpcn=ESPN&wpscn=Widget&wpcrn=BetSlipDeepLink&wpscid=__wpscid__&wpcrid=xx&preurl=https%3A%2F%2Fsportsbook.draftkings.com%2Fevent%2F34379875%3Foutcomes%3D0OU85454106O16950_1",
                    "text": "Over Odds",
                    "shortText": "Over Odds",
                    "isExternal": true,
                    "isPremium": false,
                    "tracking": {
                      "campaign": "betting-integrations",
                      "tags": {
                        "league": "wnba",
                        "sport": "basketball",
                        "gameId": 401857065,
                        "betSide": "over",
                        "betType": "straight",
                        "betDetails": "Over:169.5"
                      }
                    }
                  }
                },
                "open": {
                  "line": "o170.5",
                  "odds": "-110"
                }
              },
              "under": {
                "close": {
                  "line": "u169.5",
                  "odds": "-105",
                  "link": {
                    "language": "en-US",
                    "rel": [
                      "under",
                      "desktop",
                      "bets"
                    ],
                    "href": "https://sportsbook.draftkings.com/gateway?s=__s__&wpcid=__wpcid__&wpsrc=413&wpcn=ESPN&wpscn=Widget&wpcrn=BetSlipDeepLink&wpscid=__wpscid__&wpcrid=xx&preurl=https%3A%2F%2Fsportsbook.draftkings.com%2Fevent%2F34379875%3Foutcomes%3D0OU85454106U16950_3",
                    "text": "Under Odds",
                    "shortText": "Under Odds",
                    "isExternal": true,
                    "isPremium": false,
                    "tracking": {
                      "campaign": "betting-integrations",
                      "tags": {
                        "league": "wnba",
                        "sport": "basketball",
                        "gameId": 401857065,
                        "betSide": "under",
                        "betType": "straight",
                        "betDetails": "Under:169.5"
                      }
                    }
                  }
                },
                "open": {
                  "line": "u170.5",
                  "odds": "-110"
                }
              }
            },
            "link": {
              "language": "en-US",
              "rel": [
                "game",
                "desktop",
                "bets"
              ],
              "href": "https://sportsbook.draftkings.com/gateway?s=__s__&wpcid=__wpcid__&wpsrc=413&wpcn=ESPN&wpscn=Widget&wpcrn=BetSlipDeepLink&wpscid=__wpscid__&wpcrid=xx&preurl=https%3A%2F%2Fsportsbook.draftkings.com%2Fevent%2F34379875",
              "text": "See More Odds",
              "shortText": "Game",
              "isExternal": true,
              "isPremium": false,
              "tracking": {
                "campaign": "betting-integrations",
                "tags": {
                  "league": "wnba",
                  "sport": "basketball",
                  "gameId": 401857065,
                  "betSide": "none",
                  "betType": "straight"
                }
              }
            },
            "header": {
              "logo": {
                "dark": "https://a.espncdn.com/i/espnbet/dark/espn-bet-square-off.svg",
                "light": "https://a.espncdn.com/i/espnbet/espn-bet-square-off.svg",
                "exclusivesLogoDark": "https://a.espncdn.com/i/espnbet/espn-bet-square-mint.svg",
                "exclusivesLogoLight": "https://a.espncdn.com/i/espnbet/espn-bet-square-mint.svg"
              },
              "text": "Game Odds"
            },
            "footer": {
              "disclaimer": "GAMBLING PROBLEM? CALL 1-800-GAMBLER or 1-800-MY-RESET, (800) 327-5050 or visit gamblinghelplinema.org (MA). Call 877-8-HOPENY/text HOPENY (467369) (NY). Call 888-789-7777/visit ccpg.org (CT), or visit www.mdgamblinghelp.org (MD), 1-800-981-0023 (PR). 21+ and present in most states. (18+ DC/KY/NH/PR/WY). Void in ONT. Eligibility restrictions apply. Terms: draftkings.com/sportsbook. On behalf of Boot Hill Casino (KS). Pass-thru of per wager tax may apply in IL."
            }
          }
        ],
        "highlights": []
      }
    ],
    "links": [
      {
        "language": "en-US",
        "rel": [
          "summary",
          "desktop",
          "event"
        ],
        "href": "https://www.espn.com/wnba/game/_/gameId/401857065/mercury-lynx",
        "text": "Gamecast",
        "shortText": "Gamecast",
        "isExternal": false,
        "isPremium": false
      }
    ],
    "status": {
      "clock": 0.0,
      "displayClock": "0.0",
      "period": 0,
      "type": {
        "id": "1",
        "name": "STATUS_SCHEDULED",
        "state": "pre",
        "completed": false,
        "description": "Scheduled",
        "detail": "Mon, July 13th at 9:00 PM EDT",
        "shortDetail": "7/13 - 9:00 PM EDT"
      }
    }
  }
]